py_allotax-1.0.4.dist-info/METADATA
py_allotax-1.0.4.dist-info/WHEEL
py_allotax-1.0.4.dist-info/entry_points.txt
py_allotax-1.0.4.dist-info/licenses/LICENSE
py_allotax/__init__.py
py_allotax/generate_svg.py
py_allotax/generate_svg_minimum.js
py_allotax/package-lock.json
py_allotax/package.json
py_allotax/utils.py
py_allotax-1.0.4.dist-info/RECORD
