Metadata-Version: 2.4
Name: py-allotax
Version: 1.0.4
Summary: Python implementation of allotaxonometer to produce static graphs.
Author-Email: Computational StoryLab <jonathanstonge7@gmail.com>
License-Expression: MIT
Requires-Python: >=3.11
Requires-Dist: pandas>=2.2.1
